basis_modules/__init__.py
basis_modules/helpers/__init__.py
basis_modules/helpers/importers/__init__.py
basis_modules/helpers/importers/_ideas.py
basis_modules/helpers/testing.py
basis_modules/modules/__init__.py
basis_modules/modules/alphavantage/__init__.py
basis_modules/modules/alphavantage/importers/__init__.py
basis_modules/modules/alphavantage/importers/base.py
basis_modules/modules/alphavantage/importers/import_company_overview.py
basis_modules/modules/alphavantage/importers/import_eod_prices.py
basis_modules/modules/alphavantage/schemas/AlphavantageCompanyOverview.yml
basis_modules/modules/alphavantage/schemas/AlphavantageEodPrice.yml
basis_modules/modules/alphavantage/tests/__init__.py
basis_modules/modules/alphavantage/tests/test_alphavantage.py
basis_modules/modules/bigcommerce/__init__.py
basis_modules/modules/bigcommerce/importers/__init__.py
basis_modules/modules/bigcommerce/importers/import_order_products.py
basis_modules/modules/bigcommerce/importers/import_orders.py
basis_modules/modules/bigcommerce/schemas/BigCommerceOrder.yml
basis_modules/modules/bigcommerce/schemas/BigCommerceOrderProduct.yml
basis_modules/modules/bigcommerce/tests/__init__.py
basis_modules/modules/bigcommerce/tests/test_bigcommerce.py
basis_modules/modules/business_intelligence/__init__.py
basis_modules/modules/business_intelligence/functions/__init__.py
basis_modules/modules/business_intelligence/functions/transaction_ltv_model/__init__.py
basis_modules/modules/business_intelligence/functions/transaction_ltv_model/tests/__init__.py
basis_modules/modules/business_intelligence/functions/transaction_ltv_model/tests/test_transaction_ltv_model.py
basis_modules/modules/business_intelligence/functions/transaction_ltv_model/transaction_ltv_model.py
basis_modules/modules/business_intelligence/schemas/transaction.yml
basis_modules/modules/business_intelligence/test_bi.py
basis_modules/modules/business_intelligence/tests/__init__.py
basis_modules-0.1.1.dist-info/LICENSE
basis_modules-0.1.1.dist-info/WHEEL
basis_modules-0.1.1.dist-info/METADATA
basis_modules-0.1.1.dist-info/RECORD
