Metadata-Version: 2.1
Name: basis-modules
Version: 0.1.1
Summary: Basis modules repository
License: BSD-3-Clause
Author: Ken Van Haren
Author-email: kenvanharen@gmail.com
Requires-Python: >=3.7.4,<4.0.0
Classifier: License :: OSI Approved :: BSD License
Classifier: Programming Language :: Python :: 3
Classifier: Programming Language :: Python :: 3.8
Classifier: Programming Language :: Python :: 3.9
Requires-Dist: basis-core (>=0,<1)
